bssir/__init__.py
bssir/api.py
bssir/archive_handler.py
bssir/data_cleaner.py
bssir/data_engine.py
bssir/decoder.py
bssir/external_data_manager.py
bssir/maintainer.py
bssir/metadata_reader.py
bssir/calculator/__init__.py
bssir/calculator/average.py
bssir/calculator/quantile.py
bssir/config/settings.yaml
bssir/config/settings_sample.yaml
bssir/config/settings_sample_colab.yaml
bssir/datadoc/__init__.py
bssir/datadoc/cleaned_data.py
bssir/datadoc/datadoc_utils.py
bssir/datadoc/raw_data.py
bssir/external_data/__init__.py
bssir/external_data/cleaning_scripts.py
bssir/external_data/external_data_cleaner.py
bssir/external_data/metadata.yaml
bssir/external_data/reading_scripts.py
bssir/external_data/special_sources/wb.py
bssir/metadata/_instruction.yaml
bssir/metadata/commodities.yaml
bssir/metadata/id_information.yaml
bssir/metadata/industries.yaml
bssir/metadata/industries_comprehensive.yaml
bssir/metadata/maps.yaml
bssir/metadata/occupations.yaml
bssir/metadata/occupations_comprehensive.yaml
bssir/metadata/raw_files.yaml
bssir/metadata/schema.yaml
bssir/metadata/tables.yaml
bssir/utils/__init__.py
bssir/utils/archive_utils.py
bssir/utils/argham.py
bssir/utils/download_utils.py
bssir/utils/metadata_utils.py
bssir/utils/parsing_utils.py
bssir/utils/s3.py
bssir-0.6.7.dist-info/licenses/LICENCE
bssir-0.6.7.dist-info/.gitignore
bssir-0.6.7.dist-info/METADATA
bssir-0.6.7.dist-info/WHEEL
bssir-0.6.7.dist-info/top_level.txt
bssir-0.6.7.dist-info/RECORD
