Metadata-Version: 2.4
Name: bssir
Version: 0.6.7
Summary: Shared data-loading and transformation utilities for Iranian socioeconomic surveys.
Author-email: Mohammad Amin Alavian <m.amin.alavian@gmail.com>
Project-URL: Homepage, https://github.com/Iran-Open-Data/BSSIR
Project-URL: Repository, https://github.com/Iran-Open-Data/BSSIR
Keywords: iran,survey,data,socioeconomic
Requires-Python: >=3.10
License-File: LICENCE
Requires-Dist: dbfread
Requires-Dist: pandas>=2
Requires-Dist: PyYAML
Requires-Dist: pydantic>=2
Requires-Dist: pyodbc
Requires-Dist: requests
Requires-Dist: pyarrow
Requires-Dist: tabulate
Requires-Dist: openpyxl>=3.1.5
Requires-Dist: tqdm>=4.67.1
Provides-Extra: all
Requires-Dist: boto3; extra == "all"
Requires-Dist: boto3-stubs[s3]; extra == "all"
Requires-Dist: black; extra == "all"
Requires-Dist: tabulate; extra == "all"
Requires-Dist: mkdocs; extra == "all"
Requires-Dist: mkdocs-material; extra == "all"
Requires-Dist: mkdocs-literate-nav; extra == "all"
Requires-Dist: mkdocs-autorefs; extra == "all"
Requires-Dist: mkdocstrings-python; extra == "all"
Requires-Dist: pytest; extra == "all"
Requires-Dist: ipykernel; extra == "all"
Requires-Dist: ipywidgets; extra == "all"
Requires-Dist: seaborn; extra == "all"
Provides-Extra: dev
Requires-Dist: black; extra == "dev"
Requires-Dist: mkdocs; extra == "dev"
Requires-Dist: mkdocs-material; extra == "dev"
Requires-Dist: mkdocs-literate-nav; extra == "dev"
Requires-Dist: mkdocs-autorefs; extra == "dev"
Requires-Dist: mkdocstrings-python; extra == "dev"
Requires-Dist: pytest; extra == "dev"
Provides-Extra: maintain
Requires-Dist: boto3; extra == "maintain"
Requires-Dist: boto3-stubs[s3]; extra == "maintain"
Provides-Extra: notebook
Requires-Dist: ipykernel; extra == "notebook"
Requires-Dist: ipywidgets; extra == "notebook"
Provides-Extra: plot
Requires-Dist: seaborn; extra == "plot"
Dynamic: license-file
